ziyulibs/__init__.py
ziyulibs/base/__init__.py
ziyulibs/base/zyarr.py
ziyulibs/base/zybyte.py
ziyulibs/base/zydate.py
ziyulibs/base/zydict.py
ziyulibs/base/zystr.py
ziyulibs/base/zytype.py
ziyulibs-0.1.0.dist-info/METADATA
ziyulibs-0.1.0.dist-info/WHEEL
ziyulibs-0.1.0.dist-info/top_level.txt
ziyulibs-0.1.0.dist-info/RECORD
