Metadata-Version: 2.1
Name: ziyulibs
Version: 0.1.0
Summary: 子煜的封装库
Home-page: UNKNOWN
Author: june
Author-email: UNKNOWN
License: UNKNOWN
Platform: UNKNOWN
